generated/__init__.py
generated/graphql/mixs.graphql
generated/jsonld/mixs.context.jsonld
generated/jsonld/mixs.jsonld
generated/jsonschema/mixs.schema.json
generated/mixs.py
generated/owl/mixs.owl.ttl
generated/prefixmap/mixs.yaml
generated/protobuf/mixs.proto
generated/shacl/mixs.shacl.ttl
generated/shex/mixs.shex
generated/sqlschema/mixs.sql
mixs_linkml-0.1.3.dist-info/LICENSE
mixs_linkml-0.1.3.dist-info/WHEEL
mixs_linkml-0.1.3.dist-info/METADATA
mixs_linkml-0.1.3.dist-info/RECORD
