Metadata-Version: 2.1
Name: mixs-linkml
Version: 0.1.3
Summary: A LinkML model for the MIxS standard
Home-page: https://gensc.org/mixs/
License: CC0
Keywords: MIxS,linkml,schema,data model
Author: GSC
Requires-Python: >=3.9,<4.0
Classifier: Development Status :: 4 - Beta
Classifier: Intended Audience :: Developers
Classifier: Intended Audience :: Science/Research
Classifier: License :: CC0 1.0 Universal (CC0 1.0) Public Domain Dedication
Classifier: License :: Other/Proprietary License
Classifier: Programming Language :: Python :: 3
Classifier: Programming Language :: Python :: 3 :: Only
Classifier: Programming Language :: Python :: 3.10
Classifier: Programming Language :: Python :: 3.9
Requires-Dist: linkml (>=1.1.13)
Requires-Dist: pandas
Project-URL: Documentation, https://genomicsstandardsconsortium.github.io/mixs/
Project-URL: Repository, https://github.com/GenomicsStandardsConsortium/mixs
